{"hierarchy":{"paths":[["doc:\/\/org.swift.MyProject\/documentation\/MapLibre","doc:\/\/org.swift.MyProject\/documentation\/MapLibre\/MLNMapView"]]},"sections":[],"schemaVersion":{"patch":0,"major":0,"minor":3},"identifier":{"url":"doc:\/\/org.swift.MyProject\/documentation\/MapLibre\/MLNMapView\/visibleFeaturesInRect:inStyleLayersWithIdentifiers:predicate:","interfaceLanguage":"occ"},"kind":"symbol","primaryContentSections":[{"kind":"declarations","declarations":[{"platforms":["iOS"],"tokens":[{"text":"- (","kind":"text"},{"text":"NSArray<id<MLNFeature>>","kind":"typeIdentifier","preciseIdentifier":"c:Q$objc(cs)NSArray"},{"text":" *) ","kind":"text"},{"text":"visibleFeaturesInRect:","kind":"identifier"},{"text":"(","kind":"text"},{"text":"CGRect","kind":"typeIdentifier","preciseIdentifier":"c:@S@CGRect"},{"text":") ","kind":"text"},{"text":"rect","kind":"internalParam"},{"text":" ","kind":"text"},{"text":"inStyleLayersWithIdentifiers:","kind":"identifier"},{"text":"(","kind":"text"},{"text":"NSSet<NSString *>","kind":"typeIdentifier","preciseIdentifier":"c:Q$objc(cs)NSSet"},{"text":" *) ","kind":"text"},{"text":"styleLayerIdentifiers","kind":"internalParam"},{"text":" ","kind":"text"},{"text":"predicate:","kind":"identifier"},{"text":"(","kind":"text"},{"text":"NSPredicate","kind":"typeIdentifier","preciseIdentifier":"c:objc(cs)NSPredicate"},{"text":" *) ","kind":"text"},{"text":"predicate","kind":"internalParam"},{"text":";","kind":"text"}],"languages":["occ"]}]},{"kind":"parameters","parameters":[{"content":[{"inlineContent":[{"text":"A rectangle expressed in the map view’s coordinate system.","type":"text"}],"type":"paragraph"}],"name":"rect"},{"content":[{"inlineContent":[{"text":"A set of strings that correspond to the names of","type":"text"},{"text":" ","type":"text"},{"text":"layers defined in the current style. Only the features contained in these","type":"text"},{"type":"text","text":" "},{"type":"text","text":"layers are included in the returned array."}],"type":"paragraph"}],"name":"styleLayerIdentifiers"},{"content":[{"type":"paragraph","inlineContent":[{"type":"text","text":"A predicate to filter the returned features."}]}],"name":"predicate"}]},{"kind":"content","content":[{"level":2,"text":"Return Value","type":"heading","anchor":"return-value"},{"type":"paragraph","inlineContent":[{"text":"An array of objects conforming to the ","type":"text"},{"identifier":"doc:\/\/org.swift.MyProject\/documentation\/MapLibre\/MLNFeature","type":"reference","isActive":true},{"text":" protocol that","type":"text"},{"text":" ","type":"text"},{"text":"represent features in the sources used by the current style.","type":"text"}]}]},{"kind":"content","content":[{"level":2,"anchor":"discussion","text":"Discussion","type":"heading"},{"inlineContent":[{"type":"text","text":"Each object in the returned array represents a feature rendered by the"},{"type":"text","text":" "},{"type":"text","text":"current style and provides access to attributes specified by the relevant map"},{"type":"text","text":" "},{"type":"text","text":"content sources. The returned array includes features loaded by"},{"type":"text","text":" "},{"identifier":"doc:\/\/org.swift.MyProject\/documentation\/MapLibre\/MLNShapeSource","isActive":true,"type":"reference"},{"type":"text","text":" and "},{"identifier":"doc:\/\/org.swift.MyProject\/documentation\/MapLibre\/MLNShapeSource","isActive":true,"type":"reference"},{"type":"text","text":" objects but does not include"},{"type":"text","text":" "},{"type":"text","text":"anything from "},{"identifier":"doc:\/\/org.swift.MyProject\/documentation\/MapLibre\/MLNRasterTileSource","isActive":true,"type":"reference"},{"type":"text","text":" objects, or from video or canvas sources,"},{"type":"text","text":" "},{"type":"text","text":"which are unsupported by this SDK."}],"type":"paragraph"},{"inlineContent":[{"type":"text","text":"The returned features are drawn by a style layer in the current style. For"},{"type":"text","text":" "},{"type":"text","text":"example, suppose the current style uses a particular source,"},{"type":"text","text":" "},{"type":"text","text":"but none of the specified style layers includes features that have the "},{"code":"maki","type":"codeVoice"},{"type":"text","text":" "},{"type":"text","text":"property set to "},{"code":"bus","type":"codeVoice"},{"type":"text","text":". If you pass a rectangle containing the location of a bus"},{"type":"text","text":" "},{"type":"text","text":"stop into this method, the bus stop feature does not appear in the resulting"},{"type":"text","text":" "},{"type":"text","text":"array. On the other hand, if the style does include bus stops, an "},{"type":"reference","isActive":true,"identifier":"doc:\/\/org.swift.MyProject\/documentation\/MapLibre\/MLNFeature"},{"type":"text","text":" "},{"type":"text","text":"object representing that bus stop is returned and its "},{"type":"codeVoice","code":"featureAttributes"},{"type":"text","text":" "},{"type":"text","text":"dictionary has the "},{"type":"codeVoice","code":"maki"},{"type":"text","text":" key set to "},{"code":"bus","type":"codeVoice"},{"type":"text","text":" (along with other attributes). The"},{"type":"text","text":" "},{"type":"text","text":"dictionary contains only the attributes provided by the tile source; it does"},{"type":"text","text":" "},{"type":"text","text":"not include computed attribute values or rules about how the feature is"},{"type":"text","text":" "},{"type":"text","text":"rendered by the current style."}],"type":"paragraph"},{"inlineContent":[{"text":"The returned array is sorted by z-order, starting with the topmost rendered","type":"text"},{"text":" ","type":"text"},{"text":"feature and ending with the bottommost rendered feature. A feature that is","type":"text"},{"text":" ","type":"text"},{"text":"rendered multiple times due to wrapping across the antimeridian at low zoom","type":"text"},{"text":" ","type":"text"},{"text":"levels is included only once, subject to the caveat that follows.","type":"text"}],"type":"paragraph"},{"inlineContent":[{"text":"Features come from tiled vector data or GeoJSON data that is converted to tiles","type":"text"},{"text":" ","type":"text"},{"text":"internally, so feature geometries are clipped at tile boundaries and features","type":"text"},{"text":" ","type":"text"},{"text":"may appear duplicated across tiles. For example, suppose the specified","type":"text"},{"text":" ","type":"text"},{"text":"rectangle intersects with a road that spans the screen. The resulting array","type":"text"},{"text":" ","type":"text"},{"text":"includes those parts of the road that lie within the map tiles covering the","type":"text"},{"text":" ","type":"text"},{"text":"specified rectangle, even if the road extends into other tiles. The portion of","type":"text"},{"text":" ","type":"text"},{"text":"the road within each map tile is included individually.","type":"text"}],"type":"paragraph"},{"inlineContent":[{"type":"text","text":"To find out the layer names in a particular style, view the style in"},{"type":"text","text":" "},{"type":"text","text":"Maputnik"},{"type":"text","text":"."}],"type":"paragraph"},{"inlineContent":[{"text":"Only visible features are returned. To obtain features regardless of","type":"text"},{"text":" ","type":"text"},{"text":"visibility, use the","type":"text"},{"text":" ","type":"text"},{"type":"reference","isActive":true,"identifier":"doc:\/\/org.swift.MyProject\/documentation\/MapLibre\/MLNVectorTileSource\/featuresInSourceLayersWithIdentifiers:predicate:"},{"text":" and","type":"text"},{"text":" ","type":"text"},{"type":"reference","isActive":true,"identifier":"doc:\/\/org.swift.MyProject\/documentation\/MapLibre\/MLNShapeSource\/featuresMatchingPredicate:"},{"text":" methods on the relevant sources.","type":"text"}],"type":"paragraph"}]}],"metadata":{"role":"symbol","remoteSource":{"fileName":"MLNMapView.h","url":"https:\/\/github.com\/maplibre\/maplibre-native\/blob\/main\/platform\/ios\/src\/MLNMapView.h#L2207"},"fragments":[{"text":"- ","kind":"text"},{"text":"visibleFeaturesInRect:inStyleLayersWithIdentifiers:predicate:","kind":"identifier"}],"symbolKind":"method","title":"visibleFeaturesInRect:inStyleLayersWithIdentifiers:predicate:","modules":[{"name":"MapLibre"}],"roleHeading":"Instance Method","navigatorTitle":[{"kind":"identifier","text":"visibleFeaturesInRect:inStyleLayersWithIdentifiers:predicate:"}],"externalID":"c:objc(cs)MLNMapView(im)visibleFeaturesInRect:inStyleLayersWithIdentifiers:predicate:"},"abstract":[{"type":"text","text":"Returns an array of rendered map features that intersect with the given"},{"type":"text","text":" "},{"type":"text","text":"rectangle, restricted to the given style layers and filtered by the given"},{"type":"text","text":" "},{"type":"text","text":"predicate."}],"variants":[{"traits":[{"interfaceLanguage":"occ"}],"paths":["\/documentation\/maplibre\/mlnmapview\/visiblefeaturesinrect:instylelayerswithidentifiers:predicate:"]}],"references":{"doc://org.swift.MyProject/documentation/MapLibre/MLNShapeSource/featuresMatchingPredicate:":{"abstract":[{"text":"Returns an array of map features for this source, filtered by the given","type":"text"},{"text":" ","type":"text"},{"text":"predicate.","type":"text"}],"fragments":[{"kind":"text","text":"- "},{"kind":"identifier","text":"featuresMatchingPredicate:"}],"navigatorTitle":[{"kind":"identifier","text":"featuresMatchingPredicate:"}],"url":"\/documentation\/maplibre\/mlnshapesource\/featuresmatchingpredicate:","identifier":"doc:\/\/org.swift.MyProject\/documentation\/MapLibre\/MLNShapeSource\/featuresMatchingPredicate:","kind":"symbol","role":"symbol","title":"featuresMatchingPredicate:","type":"topic"},"doc://org.swift.MyProject/documentation/MapLibre/MLNRasterStyleLayer":{"abstract":[{"text":"An ","type":"text"},{"isActive":true,"type":"reference","identifier":"doc:\/\/org.swift.MyProject\/documentation\/MapLibre\/MLNRasterStyleLayer"},{"text":" is a style layer that renders georeferenced raster","type":"text"},{"text":" ","type":"text"},{"text":"imagery on the map, especially raster tiles.","type":"text"}],"url":"\/documentation\/maplibre\/mlnrasterstylelayer","type":"topic","role":"symbol","kind":"symbol","identifier":"doc:\/\/org.swift.MyProject\/documentation\/MapLibre\/MLNRasterStyleLayer","fragments":[{"text":"MLNRasterStyleLayer","kind":"identifier"}],"title":"MLNRasterStyleLayer"},"doc://org.swift.MyProject/documentation/MapLibre":{"title":"MapLibre","abstract":[{"type":"text","text":"Powerful, free and open-source mapping toolkit with full control over data sources and styling."}],"identifier":"doc:\/\/org.swift.MyProject\/documentation\/MapLibre","url":"\/documentation\/maplibre","role":"collection","type":"topic","kind":"symbol"},"doc://org.swift.MyProject/documentation/MapLibre/MLNMapView":{"url":"\/documentation\/maplibre\/mlnmapview","role":"symbol","identifier":"doc:\/\/org.swift.MyProject\/documentation\/MapLibre\/MLNMapView","title":"MLNMapView","abstract":[{"type":"text","text":"An interactive, customizable map view with an interface similar to the one"},{"type":"text","text":" "},{"type":"text","text":"provided by Apple’s MapKit."}],"type":"topic","fragments":[{"text":"MLNMapView","kind":"identifier"}],"kind":"symbol"},"doc://org.swift.MyProject/documentation/MapLibre/MLNVectorTileSource/featuresInSourceLayersWithIdentifiers:predicate:":{"identifier":"doc:\/\/org.swift.MyProject\/documentation\/MapLibre\/MLNVectorTileSource\/featuresInSourceLayersWithIdentifiers:predicate:","kind":"symbol","navigatorTitle":[{"text":"featuresInSourceLayersWithIdentifiers:predicate:","kind":"identifier"}],"type":"topic","fragments":[{"text":"- ","kind":"text"},{"text":"featuresInSourceLayersWithIdentifiers:predicate:","kind":"identifier"}],"title":"featuresInSourceLayersWithIdentifiers:predicate:","url":"\/documentation\/maplibre\/mlnvectortilesource\/featuresinsourcelayerswithidentifiers:predicate:","role":"symbol","abstract":[{"text":"Returns an array of map features loaded by this source, restricted to the given","type":"text"},{"text":" ","type":"text"},{"text":"source layers and filtered by the given predicate.","type":"text"}]},"doc://org.swift.MyProject/documentation/MapLibre/MLNShape":{"identifier":"doc:\/\/org.swift.MyProject\/documentation\/MapLibre\/MLNShape","abstract":[{"identifier":"doc:\/\/org.swift.MyProject\/documentation\/MapLibre\/MLNShape","type":"reference","isActive":true},{"text":" is an abstract class that represents a shape or annotation. Shapes","type":"text"},{"text":" ","type":"text"},{"text":"constitute the content of a map — not only the overlays atop the map, but also","type":"text"},{"text":" ","type":"text"},{"text":"the content that forms the base map.","type":"text"}],"type":"topic","url":"\/documentation\/maplibre\/mlnshape","kind":"symbol","fragments":[{"text":"MLNShape","kind":"identifier"}],"title":"MLNShape","role":"symbol"},"doc://org.swift.MyProject/documentation/MapLibre/MLNRasterTileSource":{"role":"symbol","title":"MLNRasterTileSource","kind":"symbol","fragments":[{"text":"MLNRasterTileSource","kind":"identifier"}],"abstract":[{"identifier":"doc:\/\/org.swift.MyProject\/documentation\/MapLibre\/MLNRasterTileSource","type":"reference","isActive":true},{"text":" is a map content source that supplies raster image tiles","type":"text"},{"text":" ","type":"text"},{"text":"to be shown on the map. The location of and metadata about the tiles are","type":"text"},{"text":" ","type":"text"},{"text":"defined either by an option dictionary or by an external file that conforms to","type":"text"},{"text":" ","type":"text"},{"text":"the","type":"text"},{"text":" ","type":"text"},{"text":"TileJSON specification","type":"text"},{"text":".","type":"text"},{"type":"text","text":" "},{"type":"text","text":"A raster tile source is added to an "},{"type":"reference","identifier":"doc:\/\/org.swift.MyProject\/documentation\/MapLibre\/MLNStyle","isActive":true},{"type":"text","text":" object along with one or more"},{"type":"text","text":" "},{"type":"reference","identifier":"doc:\/\/org.swift.MyProject\/documentation\/MapLibre\/MLNRasterStyleLayer","isActive":true},{"type":"text","text":" objects. Use a raster style layer to control the"},{"type":"text","text":" "},{"type":"text","text":"appearance of content supplied by the raster tile source."}],"identifier":"doc:\/\/org.swift.MyProject\/documentation\/MapLibre\/MLNRasterTileSource","type":"topic","url":"\/documentation\/maplibre\/mlnrastertilesource"},"doc://org.swift.MyProject/documentation/MapLibre/MLNMapView/visibleFeaturesInRect:inStyleLayersWithIdentifiers:predicate:":{"fragments":[{"kind":"text","text":"- "},{"kind":"identifier","text":"visibleFeaturesInRect:inStyleLayersWithIdentifiers:predicate:"}],"kind":"symbol","identifier":"doc:\/\/org.swift.MyProject\/documentation\/MapLibre\/MLNMapView\/visibleFeaturesInRect:inStyleLayersWithIdentifiers:predicate:","type":"topic","title":"visibleFeaturesInRect:inStyleLayersWithIdentifiers:predicate:","navigatorTitle":[{"kind":"identifier","text":"visibleFeaturesInRect:inStyleLayersWithIdentifiers:predicate:"}],"role":"symbol","abstract":[{"type":"text","text":"Returns an array of rendered map features that intersect with the given"},{"type":"text","text":" "},{"type":"text","text":"rectangle, restricted to the given style layers and filtered by the given"},{"type":"text","text":" "},{"type":"text","text":"predicate."}],"url":"\/documentation\/maplibre\/mlnmapview\/visiblefeaturesinrect:instylelayerswithidentifiers:predicate:"},"doc://org.swift.MyProject/documentation/MapLibre/MLNFeature":{"identifier":"doc:\/\/org.swift.MyProject\/documentation\/MapLibre\/MLNFeature","type":"topic","abstract":[{"type":"text","text":"The "},{"type":"reference","identifier":"doc:\/\/org.swift.MyProject\/documentation\/MapLibre\/MLNFeature","isActive":true},{"type":"text","text":"  protocol is used to provide details about geographic features"},{"type":"text","text":" "},{"type":"text","text":"contained in an "},{"type":"reference","identifier":"doc:\/\/org.swift.MyProject\/documentation\/MapLibre\/MLNShapeSource","isActive":true},{"type":"text","text":" or "},{"type":"reference","identifier":"doc:\/\/org.swift.MyProject\/documentation\/MapLibre\/MLNVectorTileSource","isActive":true},{"type":"text","text":" object. Each concrete"},{"type":"text","text":" "},{"type":"text","text":"subclass of "},{"type":"reference","identifier":"doc:\/\/org.swift.MyProject\/documentation\/MapLibre\/MLNShape","isActive":true},{"type":"text","text":" in turn has a subclass that conforms to this protocol. A"},{"type":"text","text":" "},{"type":"text","text":"feature object associates a shape with an optional identifier and attributes."}],"kind":"symbol","fragments":[{"kind":"identifier","text":"MLNFeature"}],"role":"symbol","title":"MLNFeature","url":"\/documentation\/maplibre\/mlnfeature"},"doc://org.swift.MyProject/documentation/MapLibre/MLNVectorTileSource":{"type":"topic","identifier":"doc:\/\/org.swift.MyProject\/documentation\/MapLibre\/MLNVectorTileSource","role":"symbol","abstract":[{"type":"reference","identifier":"doc:\/\/org.swift.MyProject\/documentation\/MapLibre\/MLNVectorTileSource","isActive":true},{"type":"text","text":" is a map content source that supplies tiled vector data"},{"type":"text","text":" "},{"type":"text","text":"in "},{"type":"text","text":"Mapbox Vector Tile"},{"type":"text","text":" format"},{"type":"text","text":" "},{"type":"text","text":"to be shown on the map. The location of and metadata about the tiles are"},{"type":"text","text":" "},{"type":"text","text":"defined either by an option dictionary or by an external file that conforms to"},{"type":"text","text":" "},{"type":"text","text":"the"},{"type":"text","text":" "},{"type":"text","text":"TileJSON specification"},{"type":"text","text":"."},{"type":"text","text":" "},{"type":"text","text":"A vector tile source is added to an "},{"type":"reference","identifier":"doc:\/\/org.swift.MyProject\/documentation\/MapLibre\/MLNStyle","isActive":true},{"type":"text","text":" object along with one or more"},{"type":"text","text":" "},{"type":"reference","identifier":"doc:\/\/org.swift.MyProject\/documentation\/MapLibre\/MLNVectorStyleLayer","isActive":true},{"type":"text","text":" objects. A vector style layer defines the appearance of"},{"type":"text","text":" "},{"type":"text","text":"any content supplied by the vector tile source."}],"kind":"symbol","fragments":[{"kind":"identifier","text":"MLNVectorTileSource"}],"url":"\/documentation\/maplibre\/mlnvectortilesource","title":"MLNVectorTileSource"},"doc://org.swift.MyProject/documentation/MapLibre/MLNShapeSource":{"url":"\/documentation\/maplibre\/mlnshapesource","fragments":[{"kind":"identifier","text":"MLNShapeSource"}],"role":"symbol","title":"MLNShapeSource","kind":"symbol","type":"topic","abstract":[{"isActive":true,"identifier":"doc:\/\/org.swift.MyProject\/documentation\/MapLibre\/MLNShapeSource","type":"reference"},{"type":"text","text":" is a map content source that supplies vector shapes to be"},{"type":"text","text":" "},{"type":"text","text":"shown on the map. The shapes may be instances of "},{"isActive":true,"identifier":"doc:\/\/org.swift.MyProject\/documentation\/MapLibre\/MLNShape","type":"reference"},{"type":"text","text":" or "},{"isActive":true,"identifier":"doc:\/\/org.swift.MyProject\/documentation\/MapLibre\/MLNShape","type":"reference"},{"type":"text","text":","},{"type":"text","text":" "},{"type":"text","text":"or they may be defined by local or external"},{"type":"text","text":" "},{"type":"text","text":"GeoJSON"},{"type":"text","text":" code. A shape source is added to an"},{"type":"text","text":" "},{"isActive":true,"identifier":"doc:\/\/org.swift.MyProject\/documentation\/MapLibre\/MLNStyle","type":"reference"},{"type":"text","text":" object along with an "},{"isActive":true,"identifier":"doc:\/\/org.swift.MyProject\/documentation\/MapLibre\/MLNStyle","type":"reference"},{"type":"text","text":" object. The vector style"},{"type":"text","text":" "},{"type":"text","text":"layer defines the appearance of any content supplied by the shape source. You"},{"type":"text","text":" "},{"type":"text","text":"can update a shape source by setting its "},{"type":"codeVoice","code":"shape"},{"type":"text","text":" or "},{"type":"codeVoice","code":"URL"},{"type":"text","text":" property."}],"identifier":"doc:\/\/org.swift.MyProject\/documentation\/MapLibre\/MLNShapeSource"},"doc://org.swift.MyProject/documentation/MapLibre/MLNStyle":{"identifier":"doc:\/\/org.swift.MyProject\/documentation\/MapLibre\/MLNStyle","abstract":[{"text":"The proxy object for the current map style.","type":"text"}],"fragments":[{"kind":"identifier","text":"MLNStyle"}],"role":"symbol","kind":"symbol","url":"\/documentation\/maplibre\/mlnstyle","type":"topic","title":"MLNStyle"}}}